{
  "actual_total_local_buffer_size": 44901312,
  "allocated_local_buffer_size": 4294967296,
  "build": {
    "dist_comps": 0,
    "index_size": 0,
    "max_level": 0,
    "rdma_reads_in_bytes": 0,
    "rdma_writes_in_bytes": 0,
    "remote_allocations": 0
  },
  "cache": {
    "cache_buckets_size": 454360,
    "cached_nodes": 0,
    "hit_rate": 0.0,
    "hits_total": 0,
    "local_hit_rates": {
      "c0": 0.0
    },
    "local_size": 0,
    "misses_total": 0,
    "num_cache_buckets": 11359,
    "num_cooling_table_buckets": 190
  },
  "distance": "squared_l2",
  "estimated_total_index_size": 876077260,
  "hnsw_parameters": {
    "ef_construction": 200,
    "ef_search": 100,
    "k": 10,
    "m": 32
  },
  "lavd_region_registered_bytes_per_mn": 17179869184,
  "lavd_region_registered_bytes_total": 17179869184,
  "lavd_region_requested_bytes": 17179869184,
  "lavd_region_resolved_bytes": 17179869184,
  "meta": {
    "compute_nodes": 1,
    "compute_threads": 16,
    "coroutines_per_thread": 8,
    "dataset": "gist200k",
    "hyperthreading": "true",
    "label": "gist200k_budget_f75_measure_r2",
    "memory_nodes": 1,
    "query_suffix": "uniform",
    "threads_pinned": "true",
    "timestamp": {
      "$date": "2026-07-15T05:01:36Z"
    },
    "zipf_parameter": "niform"
  },
  "neighborlist_size": 260,
  "neighborlist_size_l0": 516,
  "node_size": 3856,
  "num_queries": 1000,
  "num_vectors": 200000,
  "queries": {
    "compute_recall": "true",
    "cwc_batched_reads": 0,
    "cwc_batches": 0,
    "dist_comps": 2442121,
    "local_cn_read_bytes_gini": 0.0,
    "local_cn_read_bytes_per_mn": [
      3352233388
    ],
    "local_cn_read_submits_gini": 0.0,
    "local_cn_read_submits_per_mn": [
      103793
    ],
    "local_cn_read_wrs_gini": 0.0,
    "local_cn_read_wrs_per_mn": [
      154913
    ],
    "local_latency_p50_us": 37110.343,
    "local_latency_p95_us": 41990.483,
    "local_latency_p99_us": 43756.964,
    "local_latency_samples": 1000,
    "posts_l0": 104913,
    "posts_rerank": 50000,
    "posts_upnav": 0,
    "processed": 1000,
    "processed_local": {
      "c0": 1000
    },
    "queries_per_sec": 3407,
    "rdma_cqes": 103793,
    "rdma_posts": 103793,
    "rdma_reads_in_bytes": 3352233388,
    "rdma_writes_in_bytes": 0,
    "rdma_wrs": 154913,
    "recall": 0.9512,
    "rerank_chunks": 1000,
    "visited_neighborlists": 101153,
    "visited_nodes": 0,
    "visited_nodes_l0": 2392121
  },
  "query_contexts": 16,
  "timings": {
    "build_c0": 0.0,
    "build_max": 0.0,
    "crane_build_multi": 119.651776,
    "lavd_build_encode": 386.336317,
    "lavd_build_fetch": 1102.44316,
    "lavd_build_materialize": 9468.014862,
    "lavd_build_metadata": 17.857563,
    "lavd_build_multi": 11302.667797,
    "lavd_build_parse": 36.794655,
    "lavd_build_rank": 290.59555,
    "placement_fetch": 72.348373,
    "placement_kmeans": 727.61761,
    "query_c0": 293.482376,
    "query_max": 293.482376,
    "routing": 0.0
  }
}
