{
  "binary_sha256": "8e9bcba566e474ce7a2ab6d2a503f1d7ace02d0f8b6c4e65848379d852567ad5",
  "campaign_id": "vldb-multicn-formal-20260719f",
  "cn_count": 2,
  "dataset": "DEEP1M",
  "groundtruth_canonical_sha256": "edce835964026fe3161d1c3c0a9fdf5144fae22ee30d9b55585bebfca0117ce5",
  "kind": "vldb_multicn_raw_source",
  "metrics": {
    "bytes_per_query": null,
    "expected_queries": 10000,
    "failed_queries": 0,
    "fairness": 0.9999996826168841,
    "p50_us": null,
    "p99_us": null,
    "posts_per_query": null,
    "processed_queries": 10000,
    "qps": 813.4516292126184,
    "recall": 0.9089200049499999
  },
  "protocol_fingerprint": "3d307e42c0d412aafe221f2973d2a55b78b46ea919fe76421e3080367d3b17ec",
  "query_canonical_sha256": "68973a8fa5af6691d904c0f5a292136be6e3f21fed6b28154a1bfbdb1c93db57",
  "raw_measurements": [
    {
      "average_latency_us": 15753.835,
      "compute_us": 7325.287,
      "deserialize_us": 1713.607,
      "detail_error": null,
      "detail_scope": "complete_per_thread_text",
      "expected_queries": 5000,
      "failed_queries": 0,
      "log": "query_data_path: ../datasets/deep1M/deep1M_query.fvecs\nReading from vector 1 to -1\nSeekg position: 0 bytes\nEach vector size: 388 bytes (dim=96)\nReading 5000 vectors\nReading 5000 vectors\nQUERY_GT_SHAPE query_rows=5000 ground_truth_rows=5000 query_rows_per_ground_truth=1\noriginal_n_query_data = 5000\nsampling_mod = 1, sampling_count = 0\nquery_data.size(): 480000\nground_truth.size(): 500000\nFRONTIER_QUERY_POOL total_queries=5000 threads=10 top_k=10 fixed=1\nqueries_per_thread: 500\nground_truth.size(): 500000\nUsing physical cores only (skipping hyperthreads)\n\u001b[35m[search_client_pipelined_reuse_thread.cc:234] Thread 0 fetch QP authentication key: 42999170\n\u001b[0m\u001b[35m[search_client_pipelined_reuse_thread.cc:238] Thread 0 RDMA resources initialized\n\u001b[0m\u001b[35m[search_client_pipelined_reuse_thread.cc:234] Thread 1 fetch QP authentication key: 135497281\n\u001b[0m\u001b[35m[search_client_pipelined_reuse_thread.cc:238] Thread 1 RDMA resources initialized\n\u001b[0m\u001b[35m[search_client_pipelined_reuse_thread.cc:234] Thread 2 fetch QP authentication key: 511702305\n\u001b[0m\u001b[35m[search_client_pipelined_reuse_thread.cc:238] Thread 2 RDMA resources initialized\n\u001b[0m\u001b[35m[search_client_pipelined_reuse_thread.cc:234] Thread 3 fetch QP authentication key: 1937477084\n\u001b[0m\u001b[35m[search_client_pipelined_reuse_thread.cc:238] Thread 3 RDMA resources initialized\n\u001b[0m\u001b[35m[search_client_pipelined_reuse_thread.cc:234] Thread 4 fetch QP authentication key: 572660336\n\u001b[0m\u001b[35m[search_client_pipelined_reuse_thread.cc:238] Thread 4 RDMA resources initialized\n\u001b[0m\u001b[35m[search_client_pipelined_reuse_thread.cc:234] Thread 5 fetch QP authentication key: 1159126505\n\u001b[0m\u001b[35m[search_client_pipelined_reuse_thread.cc:238] Thread 5 RDMA resources initialized\n\u001b[0m\u001b[35m[search_client_pipelined_reuse_thread.cc:234] Thread 6 fetch QP authentication key: 1632621729\n\u001b[0m\u001b[35m[search_client_pipelined_reuse_thread.cc:238] Thread 6 RDMA resources initialized\n\u001b[0m\u001b[35m[search_client_pipelined_reuse_thread.cc:234] Thread 7 fetch QP authentication key: 1433925857\n\u001b[0m\u001b[35m[search_client_pipelined_reuse_thread.cc:238] Thread 7 RDMA resources initialized\n\u001b[0m\u001b[35m[search_client_pipelined_reuse_thread.cc:234] Thread 8 fetch QP authentication key: 1141616124\n\u001b[0m\u001b[35m[search_client_pipelined_reuse_thread.cc:238] Thread 8 RDMA resources initialized\n\u001b[0m\u001b[35m[search_client_pipelined_reuse_thread.cc:234] Thread 9 fetch QP authentication key: 939819582\n\u001b[0m\u001b[35m[search_client_pipelined_reuse_thread.cc:238] Thread 9 RDMA resources initialized\n\u001b[0m=== gRPC Service Parameters Debug ===\nepoch: 0\nrdma_base_offset: 0\nserialized_meta_hnsw size: 105066 bytes\noffset size: 320 elements\noffset_para size: 1440 elements\noverflow size: 480 elements\nmapping size: 160 elements\nThread 0 local_hnsw mapping size: 160\ndeserialize_worker start\nsearch_worker start\n=== Thread 0 testing EF = 200 for 20 seconds ===\nfetch_worker start\n=== gRPC Service Parameters Debug ===\nepoch: 0\nrdma_base_offset: 0\nserialized_meta_hnsw size: 105066 bytes\noffset size: 320 elements\noffset_para size: 1440 elements\noverflow size: 480 elements\nmapping size: 160 elements\nThread 1 local_hnsw mapping size: 160\ndeserialize_worker start\nfetch_worker start\nsearch_worker start\n=== Thread 1 testing EF = 200 for 20 seconds ===\n=== gRPC Service Parameters Debug ===\nepoch: 0\nrdma_base_offset: 0\nserialized_meta_hnsw size: 105066 bytes\noffset size: 320 elements\noffset_para size: 1440 elements\noverflow size: 480 elements\nmapping size: 160 elements\nThread 2 local_hnsw mapping size: 160\nfetch_worker start\ndeserialize_worker start\nsearch_worker start\n=== Thread 2 testing EF = 200 for 20 seconds ===\n=== gRPC Service Parameters Debug ===\nepoch: 0\nrdma_base_offset: 0\nserialized_meta_hnsw size: 105066 bytes\noffset size: 320 elements\noffset_para size: 1440 elements\noverflow size: 480 elements\nmapping size: 160 elements\nThread 3 local_hnsw mapping size: 160\nfetch_worker start\ndeserialize_worker start\nsearch_worker start\n=== Thread 3 testing EF = 200 for 20 seconds ===\n=== gRPC Service Parameters Debug ===\nepoch: 0\nrdma_base_offset: 0\nserialized_meta_hnsw size: 105066 bytes\noffset size: 320 elements\noffset_para size: 1440 elements\noverflow size: 480 elements\nmapping size: 160 elements\nThread 4 local_hnsw mapping size: 160\nfetch_worker start\ndeserialize_worker start\nsearch_worker start\n=== Thread 4 testing EF = 200 for 20 seconds ===\n=== gRPC Service Parameters Debug ===\nepoch: 0\nrdma_base_offset: 0\nserialized_meta_hnsw size: 105066 bytes\noffset size: 320 elements\noffset_para size: 1440 elements\noverflow size: 480 elements\nmapping size: 160 elements\nThread 5 local_hnsw mapping size: 160\nfetch_worker start\ndeserialize_worker start\n=== Thread 5 testing EF = 200 for 20 seconds ===\nsearch_worker start\n=== gRPC Service Parameters Debug ===\nepoch: 0\nrdma_base_offset: 0\nserialized_meta_hnsw size: 105066 bytes\noffset size: 320 elements\noffset_para size: 1440 elements\noverflow size: 480 elements\nmapping size: 160 elements\nThread 6 local_hnsw mapping size: 160\nfetch_worker start\ndeserialize_worker start\nsearch_worker start\n=== Thread 6 testing EF = 200 for 20 seconds ===\n=== gRPC Service Parameters Debug ===\nepoch: 0\nrdma_base_offset: 0\nserialized_meta_hnsw size: 105066 bytes\noffset size: 320 elements\noffset_para size: 1440 elements\noverflow size: 480 elements\nmapping size: 160 elements\nThread 7 local_hnsw mapping size: 160\nfetch_worker start\ndeserialize_worker start\nsearch_worker start\n=== Thread 7 testing EF = 200 for 20 seconds ===\n=== gRPC Service Parameters Debug ===\nepoch: 0\nrdma_base_offset: 0\nserialized_meta_hnsw size: 105066 bytes\noffset size: 320 elements\noffset_para size: 1440 elements\noverflow size: 480 elements\nmapping size: 160 elements\nThread 8 local_hnsw mapping size: 160\nfetch_worker start\ndeserialize_worker start\nsearch_worker start\n=== Thread 8 testing EF = 200 for 20 seconds ===\n=== gRPC Service Parameters Debug ===\nepoch: 0\nrdma_base_offset: 0\nserialized_meta_hnsw size: 105066 bytes\noffset size: 320 elements\noffset_para size: 1440 elements\noverflow size: 480 elements\nmapping size: 160 elements\nThread 9 local_hnsw mapping size: 160\nfetch_worker start\ndeserialize_worker start\nsearch_worker start\n=== Thread 9 testing EF = 200 for 20 seconds ===\n\u001b[39m[reporter.hh:42] [Batch 0] Compute: 661,482.00 ms, Network: 110,252.00 ms, Deserialize: 942,371.00 ms, Meta Search: 7,392.00 ms, Throughput: 459.91 qps, Total Time: 1,087,180.00 ms\n\u001b[0mThread 5 EF 200 benchmark:\n  Queries executed: 500\n  Avg total latency: 2174.36 us\n  Avg meta search latency: 14.784 us\n  Avg compute time: 1322.96 us\n  Avg network latency: 220.504 us\n  Avg deserialize time: 1884.74 us\n  Recall: 0.9106\n  Throughput: 458.092 QPS\nFRONTIER_THREAD_RESULT ef=200 thread=5 queries=500 elapsed_s=1.091484431 recall=0.910600007\n\u001b[35m[search_client_pipelined_reuse_thread.cc:581] Thread 5 returns\n\u001b[0m\u001b[39m[reporter.hh:42] [Batch 0] Compute: 673,436.00 ms, Network: 113,564.00 ms, Deserialize: 959,343.00 ms, Meta Search: 5,368.00 ms, Throughput: 456.16 qps, Total Time: 1,096,105.00 ms\n\u001b[0mThread 6 EF 200 benchmark:\n  Queries executed: 500\n  Avg total latency: 2192.21 us\n  Avg meta search latency: 10.736 us\n  Avg compute time: 1346.87 us\n  Avg network latency: 227.128 us\n  Avg deserialize time: 1918.69 us\n  Recall: 0.916\n  Throughput: 454.434 QPS\nFRONTIER_THREAD_RESULT ef=200 thread=6 queries=500 elapsed_s=1.100270871 recall=0.916000009\n\u001b[35m[search_client_pipelined_reuse_thread.cc:581] Thread 6 returns\n\u001b[0m\u001b[39m[reporter.hh:42] [Batch 0] Compute: 2,986,874.00 ms, Network: 100,007.00 ms, Deserialize: 1,265,659.00 ms, Meta Search: 14,361.00 ms, Throughput: 139.93 qps, Total Time: 3,573,303.00 ms\n\u001b[0mThread 4 EF 200 benchmark:\n  Queries executed: 500\n  Avg total latency: 7146.61 us\n  Avg meta search latency: 28.722 us\n  Avg compute time: 5973.75 us\n  Avg network latency: 200.014 us\n  Avg deserialize time: 2531.32 us\n  Recall: 0.8964\n  Throughput: 139.737 QPS\nFRONTIER_THREAD_RESULT ef=200 thread=4 queries=500 elapsed_s=3.578155963 recall=0.896399975\n\u001b[35m[search_client_pipelined_reuse_thread.cc:581] Thread 4 returns\n\u001b[0m\u001b[39m[reporter.hh:42] [Batch 0] Compute: 3,125,995.00 ms, Network: 102,416.00 ms, Deserialize: 1,291,742.00 ms, Meta Search: 11,028.00 ms, Throughput: 133.65 qps, Total Time: 3,741,233.00 ms\n\u001b[0mThread 9 EF 200 benchmark:\n  Queries executed: 500\n  Avg total latency: 7482.47 us\n  Avg meta search latency: 22.056 us\n  Avg compute time: 6251.99 us\n  Avg network latency: 204.832 us\n  Avg deserialize time: 2583.48 us\n  Recall: 0.9096\n  Throughput: 133.494 QPS\nFRONTIER_THREAD_RESULT ef=200 thread=9 queries=500 elapsed_s=3.745494750 recall=0.909600019\n\u001b[35m[search_client_pipelined_reuse_thread.cc:581] Thread 9 returns\n\u001b[0m\u001b[39m[reporter.hh:42] [Batch 0] Compute: 2,762,602.00 ms, Network: 6,187,353.00 ms, Deserialize: 972,201.00 ms, Meta Search: 6,599.00 ms, Throughput: 54.70 qps, Total Time: 9,141,148.00 ms\n\u001b[0mThread 8 EF 200 benchmark:\n  Queries executed: 500\n  Avg total latency: 18282.3 us\n  Avg meta search latency: 13.198 us\n  Avg compute time: 5525.2 us\n  Avg network latency: 12374.7 us\n  Avg deserialize time: 1944.4 us\n  Recall: 0.9124\n  Throughput: 54.663 QPS\nFRONTIER_THREAD_RESULT ef=200 thread=8 queries=500 elapsed_s=9.146962492 recall=0.912400007\n\u001b[35m[search_client_pipelined_reuse_thread.cc:581] Thread 8 returns\n\u001b[0m\u001b[39m[reporter.hh:42] [Batch 0] Compute: 5,046,568.00 ms, Network: 6,615,175.00 ms, Deserialize: 546,196.00 ms, Meta Search: 8,450.00 ms, Throughput: 42.45 qps, Total Time: 11,777,186.00 ms\n\u001b[0mThread 3 EF 200 benchmark:\n  Queries executed: 500\n  Avg total latency: 23554.4 us\n  Avg meta search latency: 16.9 us\n  Avg compute time: 10093.1 us\n  Avg network latency: 13230.4 us\n  Avg deserialize time: 1092.39 us\n  Recall: 0.899\n  Throughput: 42.4413 QPS\nFRONTIER_THREAD_RESULT ef=200 thread=3 queries=500 elapsed_s=11.780991313 recall=0.898999989\n\u001b[35m[search_client_pipelined_reuse_thread.cc:581] Thread 3 returns\n\u001b[0m\u001b[39m[reporter.hh:42] [Batch 0] Compute: 5,212,542.00 ms, Network: 6,642,660.00 ms, Deserialize: 577,677.00 ms, Meta Search: 8,393.00 ms, Throughput: 41.97 qps, Total Time: 11,913,225.00 ms\n\u001b[0mThread 0 EF 200 benchmark:\n  Queries executed: 500\n  Avg total latency: 23826.5 us\n  Avg meta search latency: 16.786 us\n  Avg compute time: 10425.1 us\n  Avg network latency: 13285.3 us\n  Avg deserialize time: 1155.35 us\n  Recall: 0.9054\n  Throughput: 41.9559 QPS\nFRONTIER_THREAD_RESULT ef=200 thread=0 queries=500 elapsed_s=11.917268782 recall=0.905399978\n\u001b[35m[search_client_pipelined_reuse_thread.cc:581] Thread 0 returns\n\u001b[0m\u001b[39m[reporter.hh:42] [Batch 0] Compute: 5,313,879.00 ms, Network: 6,612,146.00 ms, Deserialize: 632,847.00 ms, Meta Search: 7,911.00 ms, Throughput: 41.52 qps, Total Time: 12,041,290.00 ms\n\u001b[0mThread 2 EF 200 benchmark:\n  Queries executed: 500\n  Avg total latency: 24082.6 us\n  Avg meta search latency: 15.822 us\n  Avg compute time: 10627.8 us\n  Avg network latency: 13224.3 us\n  Avg deserialize time: 1265.69 us\n  Recall: 0.9146\n  Throughput: 41.5108 QPS\nFRONTIER_THREAD_RESULT ef=200 thread=2 queries=500 elapsed_s=12.045066866 recall=0.914600015\n\u001b[35m[search_client_pipelined_reuse_thread.cc:581] Thread 2 returns\n\u001b[0m\u001b[39m[reporter.hh:42] [Batch 0] Compute: 5,383,925.00 ms, Network: 6,632,871.00 ms, Deserialize: 595,386.00 ms, Meta Search: 8,386.00 ms, Throughput: 41.26 qps, Total Time: 12,117,201.00 ms\n\u001b[0mThread 1 EF 200 benchmark:\n  Queries executed: 500\n  Avg total latency: 24234.4 us\n  Avg meta search latency: 16.772 us\n  Avg compute time: 10767.9 us\n  Avg network latency: 13265.7 us\n  Avg deserialize time: 1190.77 us\n  Recall: 0.91\n  Throughput: 41.2563 QPS\nFRONTIER_THREAD_RESULT ef=200 thread=1 queries=500 elapsed_s=12.119357493 recall=0.910000026\n\u001b[35m[search_client_pipelined_reuse_thread.cc:581] Thread 1 returns\n\u001b[0m\u001b[39m[reporter.hh:42] [Batch 0] Compute: 5,459,085.00 ms, Network: 6,644,401.00 ms, Deserialize: 784,618.00 ms, Meta Search: 7,732.00 ms, Throughput: 40.71 qps, Total Time: 12,281,249.00 ms\n\u001b[0mThread 7 EF 200 benchmark:\n  Queries executed: 500\n  Avg total latency: 24562.5 us\n  Avg meta search latency: 15.464 us\n  Avg compute time: 10918.2 us\n  Avg network latency: 13288.8 us\n  Avg deserialize time: 1569.24 us\n  Recall: 0.9138\n  Throughput: 40.6955 QPS\nFRONTIER_THREAD_RESULT ef=200 thread=7 queries=500 elapsed_s=12.286372214 recall=0.913800001\n\u001b[35m[search_client_pipelined_reuse_thread.cc:581] Thread 7 returns\n\u001b[0mEF: 200\nThread 0 recall: 0.9054\nThread 0 latency: 23826.5\nThread 0 network latency: 13285.3\nThread 0 duration_meta_search: 16.786\nThread 0 compute time: 10425.1\nThread 1 recall: 0.91\nThread 1 latency: 24234.4\nThread 1 network latency: 13265.7\nThread 1 duration_meta_search: 16.772\nThread 1 compute time: 10767.9\nThread 2 recall: 0.9146\nThread 2 latency: 24082.6\nThread 2 network latency: 13224.3\nThread 2 duration_meta_search: 15.822\nThread 2 compute time: 10627.8\nThread 3 recall: 0.899\nThread 3 latency: 23554.4\nThread 3 network latency: 13230.4\nThread 3 duration_meta_search: 16.9\nThread 3 compute time: 10093.1\nThread 4 recall: 0.8964\nThread 4 latency: 7146.61\nThread 4 network latency: 200.014\nThread 4 duration_meta_search: 28.722\nThread 4 compute time: 5973.75\nThread 5 recall: 0.9106\nThread 5 latency: 2174.36\nThread 5 network latency: 220.504\nThread 5 duration_meta_search: 14.784\nThread 5 compute time: 1322.96\nThread 6 recall: 0.916\nThread 6 latency: 2192.21\nThread 6 network latency: 227.128\nThread 6 duration_meta_search: 10.736\nThread 6 compute time: 1346.87\nThread 7 recall: 0.9138\nThread 7 latency: 24562.5\nThread 7 network latency: 13288.8\nThread 7 duration_meta_search: 15.464\nThread 7 compute time: 10918.2\nThread 8 recall: 0.9124\nThread 8 latency: 18282.3\nThread 8 network latency: 12374.7\nThread 8 duration_meta_search: 13.198\nThread 8 compute time: 5525.2\nThread 9 recall: 0.9096\nThread 9 latency: 7482.47\nThread 9 network latency: 204.832\nThread 9 duration_meta_search: 22.056\nThread 9 compute time: 6251.99\n",
      "machine_record_prefix_interleavings": 0,
      "meta_us": 17.124,
      "network_us": 7952.1678,
      "path": "/home/kvgroup/chaomei/graphbeyond-c1/evidence/vldb-multicn-formal-20260719f/raw/dhnsw/DEEP1M_d-HNSW_2cn_r0/c0.log",
      "processed_queries": 5000,
      "qps": 406.9549508114878,
      "recall": 0.9087800025999999,
      "sha256": "58fcb11d636acb63538c639410f17467a347b5bdb5efad55779d7508f07c18ce",
      "wall_seconds": 12.286372214
    },
    {
      "average_latency_us": 13630.228,
      "compute_us": 6481.035,
      "deserialize_us": 1480.2448,
      "detail_error": null,
      "detail_scope": "complete_per_thread_text",
      "expected_queries": 5000,
      "failed_queries": 0,
      "log": "query_data_path: ../datasets/deep1M/deep1M_query.fvecs\nReading from vector 1 to -1\nSeekg position: 0 bytes\nEach vector size: 388 bytes (dim=96)\nReading 5000 vectors\nReading 5000 vectors\nQUERY_GT_SHAPE query_rows=5000 ground_truth_rows=5000 query_rows_per_ground_truth=1\noriginal_n_query_data = 5000\nsampling_mod = 1, sampling_count = 0\nquery_data.size(): 480000\nground_truth.size(): 500000\nFRONTIER_QUERY_POOL total_queries=5000 threads=10 top_k=10 fixed=1\nqueries_per_thread: 500\nground_truth.size(): 500000\nUsing physical cores only (skipping hyperthreads)\n\u001b[35m[search_client_pipelined_reuse_thread.cc:234] Thread 0 fetch QP authentication key: 982906996\n\u001b[0m\u001b[35m[search_client_pipelined_reuse_thread.cc:238] Thread 0 RDMA resources initialized\n\u001b[0m\u001b[35m[search_client_pipelined_reuse_thread.cc:234] Thread 1 fetch QP authentication key: 2084420925\n\u001b[0m\u001b[35m[search_client_pipelined_reuse_thread.cc:238] Thread 1 RDMA resources initialized\n\u001b[0m\u001b[35m[search_client_pipelined_reuse_thread.cc:234] Thread 2 fetch QP authentication key: 1827336327\n\u001b[0m\u001b[35m[search_client_pipelined_reuse_thread.cc:238] Thread 2 RDMA resources initialized\n\u001b[0m\u001b[35m[search_client_pipelined_reuse_thread.cc:234] Thread 3 fetch QP authentication key: 805750846\n\u001b[0m\u001b[35m[search_client_pipelined_reuse_thread.cc:238] Thread 3 RDMA resources initialized\n\u001b[0m\u001b[35m[search_client_pipelined_reuse_thread.cc:234] Thread 4 fetch QP authentication key: 1100661313\n\u001b[0m\u001b[35m[search_client_pipelined_reuse_thread.cc:238] Thread 4 RDMA resources initialized\n\u001b[0m\u001b[35m[search_client_pipelined_reuse_thread.cc:234] Thread 5 fetch QP authentication key: 84353895\n\u001b[0m\u001b[35m[search_client_pipelined_reuse_thread.cc:238] Thread 5 RDMA resources initialized\n\u001b[0m\u001b[35m[search_client_pipelined_reuse_thread.cc:234] Thread 6 fetch QP authentication key: 2001100545\n\u001b[0m\u001b[35m[search_client_pipelined_reuse_thread.cc:238] Thread 6 RDMA resources initialized\n\u001b[0m\u001b[35m[search_client_pipelined_reuse_thread.cc:234] Thread 7 fetch QP authentication key: 1548233367\n\u001b[0m\u001b[35m[search_client_pipelined_reuse_thread.cc:238] Thread 7 RDMA resources initialized\n\u001b[0m\u001b[35m[search_client_pipelined_reuse_thread.cc:234] Thread 8 fetch QP authentication key: 610515434\n\u001b[0m\u001b[35m[search_client_pipelined_reuse_thread.cc:238] Thread 8 RDMA resources initialized\n\u001b[0m\u001b[35m[search_client_pipelined_reuse_thread.cc:234] Thread 9 fetch QP authentication key: 1585990364\n\u001b[0m\u001b[35m[search_client_pipelined_reuse_thread.cc:238] Thread 9 RDMA resources initialized\n\u001b[0m=== gRPC Service Parameters Debug ===\nepoch: 0\nrdma_base_offset: 0\nserialized_meta_hnsw size: 105066 bytes\noffset size: 320 elements\noffset_para size: 1440 elements\noverflow size: 480 elements\nmapping size: 160 elements\nThread 0 local_hnsw mapping size: 160\nfetch_worker start\ndeserialize_worker start\nsearch_worker start\n=== Thread 0 testing EF = 200 for 20 seconds ===\n=== gRPC Service Parameters Debug ===\nepoch: 0\nrdma_base_offset: 0\nserialized_meta_hnsw size: 105066 bytes\noffset size: 320 elements\noffset_para size: 1440 elements\noverflow size: 480 elements\nmapping size: 160 elements\nThread 1 local_hnsw mapping size: 160\nfetch_worker start\ndeserialize_worker start\n=== Thread search_worker start1\n testing EF = 200 for 20 seconds ===\n=== gRPC Service Parameters Debug ===\nepoch: 0\nrdma_base_offset: 0\nserialized_meta_hnsw size: 105066 bytes\noffset size: 320 elements\noffset_para size: 1440 elements\noverflow size: 480 elements\nmapping size: 160 elements\nThread 2 local_hnsw mapping size: 160\nfetch_worker start\ndeserialize_worker start\nsearch_worker start\n=== Thread 2 testing EF = 200 for 20 seconds ===\n=== gRPC Service Parameters Debug ===\nepoch: 0\nrdma_base_offset: 0\nserialized_meta_hnsw size: 105066 bytes\noffset size: 320 elements\noffset_para size: 1440 elements\noverflow size: 480 elements\nmapping size: 160 elements\nThread 3 local_hnsw mapping size: 160\nfetch_worker start\ndeserialize_worker start\n=== Thread search_worker start3\n testing EF = 200 for 20 seconds ===\n=== gRPC Service Parameters Debug ===\nepoch: 0\nrdma_base_offset: 0\nserialized_meta_hnsw size: 105066 bytes\noffset size: 320 elements\noffset_para size: 1440 elements\noverflow size: 480 elements\nmapping size: 160 elements\nThread 4 local_hnsw mapping size: 160\nfetch_worker start\ndeserialize_worker start\nsearch_worker start=== Thread \n4 testing EF = 200 for 20 seconds ===\n=== gRPC Service Parameters Debug ===\nepoch: 0\nrdma_base_offset: 0\nserialized_meta_hnsw size: 105066 bytes\noffset size: 320 elements\noffset_para size: 1440 elements\noverflow size: 480 elements\nmapping size: 160 elements\nThread 5 local_hnsw mapping size: 160\nfetch_worker start\ndeserialize_worker start\nsearch_worker start=== Thread \n5 testing EF = 200 for 20 seconds ===\n=== gRPC Service Parameters Debug ===\nepoch: 0\nrdma_base_offset: 0\nserialized_meta_hnsw size: 105066 bytes\noffset size: 320 elements\noffset_para size: 1440 elements\noverflow size: 480 elements\nmapping size: 160 elements\nThread 6 local_hnsw mapping size: 160\nfetch_worker start\ndeserialize_worker start\nsearch_worker start\n=== Thread 6 testing EF = 200 for 20 seconds ===\n=== gRPC Service Parameters Debug ===\nepoch: 0\nrdma_base_offset: 0\nserialized_meta_hnsw size: 105066 bytes\noffset size: 320 elements\noffset_para size: 1440 elements\noverflow size: 480 elements\nmapping size: 160 elements\nThread 7 local_hnsw mapping size: 160\nfetch_worker start\ndeserialize_worker start\n=== Thread search_worker start7\n testing EF = 200 for 20 seconds ===\n=== gRPC Service Parameters Debug ===\nepoch: 0\nrdma_base_offset: 0\nserialized_meta_hnsw size: 105066 bytes\noffset size: 320 elements\noffset_para size: 1440 elements\noverflow size: 480 elements\nmapping size: 160 elements\nThread 8 local_hnsw mapping size: 160\nfetch_worker start\ndeserialize_worker start\nsearch_worker start\n=== Thread 8 testing EF = 200 for 20 seconds ===\n=== gRPC Service Parameters Debug ===\nepoch: 0\nrdma_base_offset: 0\nserialized_meta_hnsw size: 105066 bytes\noffset size: 320 elements\noffset_para size: 1440 elements\noverflow size: 480 elements\nmapping size: 160 elements\nThread 9 local_hnsw mapping size: 160\nfetch_worker start\ndeserialize_worker start\nsearch_worker start\n=== Thread 9 testing EF = 200 for 20 seconds ===\n\u001b[39m[reporter.hh:42] [Batch 0] Compute: 731,415.00 ms, Network: 122,371.00 ms, Deserialize: 642,491.00 ms, Meta Search: 3,000.00 ms, Throughput: 522.50 qps, Total Time: 956,938.00 ms\n\u001b[0mThread 3 EF 200 benchmark:\n  Queries executed: 500\n  Avg total latency: 1913.88 us\n  Avg meta search latency: 6 us\n  Avg compute time: 1462.83 us\n  Avg network latency: 244.742 us\n  Avg deserialize time: 1284.98 us\n  Recall: 0.9098\n  Throughput: 520.854 QPS\nFRONTIER_THREAD_RESULT ef=200 thread=3 queries=500 elapsed_s=0.959962320 recall=0.909799993\n\u001b[35m[search_client_pipelined_reuse_thread.cc:581] Thread 3 returns\n\u001b[0m\u001b[39m[reporter.hh:42] [Batch 0] Compute: 743,229.00 ms, Network: 117,251.00 ms, Deserialize: 643,756.00 ms, Meta Search: 2,983.00 ms, Throughput: 517.47 qps, Total Time: 966,237.00 ms\n\u001b[0mThread 2 EF 200 benchmark:\n  Queries executed: 500\n  Avg total latency: 1932.47 us\n  Avg meta search latency: 5.966 us\n  Avg compute time: 1486.46 us\n  Avg network latency: 234.502 us\n  Avg deserialize time: 1287.51 us\n  Recall: 0.9048\n  Throughput: 516.011 QPS\nFRONTIER_THREAD_RESULT ef=200 thread=2 queries=500 elapsed_s=0.968970806 recall=0.904799998\n\u001b[35m[search_client_pipelined_reuse_thread.cc:581] Thread 2 returns\n\u001b[0m\u001b[39m[reporter.hh:42] [Batch 0] Compute: 777,548.00 ms, Network: 119,881.00 ms, Deserialize: 584,301.00 ms, Meta Search: 3,080.00 ms, Throughput: 505.82 qps, Total Time: 988,488.00 ms\n\u001b[0mThread 0 EF 200 benchmark:\n  Queries executed: 500\n  Avg total latency: 1976.98 us\n  Avg meta search latency: 6.16 us\n  Avg compute time: 1555.1 us\n  Avg network latency: 239.762 us\n  Avg deserialize time: 1168.6 us\n  Recall: 0.9066\n  Throughput: 504.592 QPS\nFRONTIER_THREAD_RESULT ef=200 thread=0 queries=500 elapsed_s=0.990899451 recall=0.906599998\n\u001b[35m[search_client_pipelined_reuse_thread.cc:581] Thread 0 returns\n\u001b[0m\u001b[39m[reporter.hh:42] [Batch 0] Compute: 1,749,632.00 ms, Network: 123,346.00 ms, Deserialize: 990,194.00 ms, Meta Search: 3,007.00 ms, Throughput: 228.89 qps, Total Time: 2,184,488.00 ms\n\u001b[0m\u001b[39m[reporter.hh:42] [Batch 0] Compute: 1,749,252.00 ms, Network: 126,526.00 ms, Deserialize: 971,290.00 ms, Meta Search: 3,237.00 ms, Throughput: 228.89 qps, Total Time: 2,184,484.00 ms\n\u001b[0mThread 5 EF 200 benchmark:\n  Queries executed: 500\n  Avg total latency: 4368.98 us\n  Avg meta search latency: 6.014 us\n  Avg compute time: 3499.26 us\n  Avg network latency: 246.692 us\n  Avg deserialize time: 1980.39 us\n  Recall: 0.9132\n  Throughput: 228.502 QPS\nFRONTIER_THREAD_RESULT ef=200 thread=5 queries=500 elapsed_s=2.188161224 recall=0.913200021\n\u001b[35m[search_client_pipelined_reuse_thread.cc:581] Thread 5 returns\n\u001b[0mThread 7 EF 200 benchmark:\n  Queries executed: 500\n  Avg total latency: 4368.97 us\n  Avg meta search latency: 6.474 us\n  Avg compute time: 3498.5 us\n  Avg network latency: 253.052 us\n  Avg deserialize time: 1942.58 us\n  Recall: 0.912\n  Throughput: 228.491 QPS\nFRONTIER_THREAD_RESULT ef=200 thread=7 queries=500 elapsed_s=2.188269316 recall=0.912000000\n\u001b[35m[search_client_pipelined_reuse_thread.cc:581] Thread 7 returns\n\u001b[0m\u001b[39m[reporter.hh:42] [Batch 0] Compute: 5,129,515.00 ms, Network: 6,660,844.00 ms, Deserialize: 480,644.00 ms, Meta Search: 3,004.00 ms, Throughput: 41.96 qps, Total Time: 11,916,487.00 ms\n\u001b[0mThread 1 EF 200 benchmark:\n  Queries executed: 500\n  Avg total latency: 23833 us\n  Avg meta search latency: 6.008 us\n  Avg compute time: 10259 us\n  Avg network latency: 13321.7 us\n  Avg deserialize time: 961.288 us\n  Recall: 0.9064\n  Throughput: 41.9507 QPS\nFRONTIER_THREAD_RESULT ef=200 thread=1 queries=500 elapsed_s=11.918741254 recall=0.906400025\n\u001b[35m[search_client_pipelined_reuse_thread.cc:581] Thread 1 returns\n\u001b[0m\u001b[39m[reporter.hh:42] [Batch 0] Compute: 5,338,449.00 ms, Network: 6,660,762.00 ms, Deserialize: 750,651.00 ms, Meta Search: 3,069.00 ms, Throughput: 41.09 qps, Total Time: 12,168,491.00 ms\n\u001b[0mThread 6 EF 200 benchmark:\n  Queries executed: 500\n  Avg total latency: 24337 us\n  Avg meta search latency: 6.138 us\n  Avg compute time: 10676.9 us\n  Avg network latency: 13321.5 us\n  Avg deserialize time: 1501.3 us\n  Recall: 0.9256\n  Throughput: 41.0771 QPS\nFRONTIER_THREAD_RESULT ef=200 thread=6 queries=500 elapsed_s=12.172219189 recall=0.925599992\n\u001b[35m[search_client_pipelined_reuse_thread.cc:581] Thread 6 returns\n\u001b[0m\u001b[39m[reporter.hh:42] [Batch 0] Compute: 5,394,107.00 ms, Network: 6,676,398.00 ms, Deserialize: 687,000.00 ms, Meta Search: 3,099.00 ms, Throughput: 40.97 qps, Total Time: 12,204,493.00 ms\n\u001b[0mThread 8 EF 200 benchmark:\n  Queries executed: 500\n  Avg total latency: 24409 us\n  Avg meta search latency: 6.198 us\n  Avg compute time: 10788.2 us\n  Avg network latency: 13352.8 us\n  Avg deserialize time: 1374 us\n  Recall: 0.9092\n  Throughput: 40.9563 QPS\nFRONTIER_THREAD_RESULT ef=200 thread=8 queries=500 elapsed_s=12.208126052 recall=0.909200013\n\u001b[35m[search_client_pipelined_reuse_thread.cc:581] Thread 8 returns\n\u001b[0m\u001b[39m[reporter.hh:42] [Batch 0] Compute: 5,391,048.00 ms, Network: 6,627,893.00 ms, Deserialize: 823,345.00 ms, Meta Search: 3,942.00 ms, Throughput: 40.70 qps, Total Time: 12,284,499.00 ms\n\u001b[0mThread 9 EF 200 benchmark:\n  Queries executed: 500\n  Avg total latency: 24569 us\n  Avg meta search latency: 7.884 us\n  Avg compute time: 10782.1 us\n  Avg network latency: 13255.8 us\n  Avg deserialize time: 1646.69 us\n  Recall: 0.901\n  Throughput: 40.6896 QPS\nFRONTIER_THREAD_RESULT ef=200 thread=9 queries=500 elapsed_s=12.288148337 recall=0.901000023\n\u001b[35m[search_client_pipelined_reuse_thread.cc:581] Thread 9 returns\n\u001b[0m\u001b[39m[reporter.hh:42] [Batch 0] Compute: 5,401,018.00 ms, Network: 6,624,039.00 ms, Deserialize: 827,553.00 ms, Meta Search: 4,050.00 ms, Throughput: 40.66 qps, Total Time: 12,296,491.00 ms\n\u001b[0mThread 4 EF 200 benchmark:\n  Queries executed: 500\n  Avg total latency: 24593 us\n  Avg meta search latency: 8.1 us\n  Avg compute time: 10802 us\n  Avg network latency: 13248.1 us\n  Avg deserialize time: 1655.11 us\n  Recall: 0.902\n  Throughput: 40.6497 QPS\nFRONTIER_THREAD_RESULT ef=200 thread=4 queries=500 elapsed_s=12.300223509 recall=0.902000010\n\u001b[35m[search_client_pipelined_reuse_thread.cc:581] Thread 4 returns\n\u001b[0mEF: 200\nThread 0 recall: 0.9066\nThread 0 latency: 1976.98\nThread 0 network latency: 239.762\nThread 0 duration_meta_search: 6.16\nThread 0 compute time: 1555.1\nThread 1 recall: 0.9064\nThread 1 latency: 23833\nThread 1 network latency: 13321.7\nThread 1 duration_meta_search: 6.008\nThread 1 compute time: 10259\nThread 2 recall: 0.9048\nThread 2 latency: 1932.47\nThread 2 network latency: 234.502\nThread 2 duration_meta_search: 5.966\nThread 2 compute time: 1486.46\nThread 3 recall: 0.9098\nThread 3 latency: 1913.88\nThread 3 network latency: 244.742\nThread 3 duration_meta_search: 6\nThread 3 compute time: 1462.83\nThread 4 recall: 0.902\nThread 4 latency: 24593\nThread 4 network latency: 13248.1\nThread 4 duration_meta_search: 8.1\nThread 4 compute time: 10802\nThread 5 recall: 0.9132\nThread 5 latency: 4368.98\nThread 5 network latency: 246.692\nThread 5 duration_meta_search: 6.014\nThread 5 compute time: 3499.26\nThread 6 recall: 0.9256\nThread 6 latency: 24337\nThread 6 network latency: 13321.5\nThread 6 duration_meta_search: 6.138\nThread 6 compute time: 10676.9\nThread 7 recall: 0.912\nThread 7 latency: 4368.97\nThread 7 network latency: 253.052\nThread 7 duration_meta_search: 6.474\nThread 7 compute time: 3498.5\nThread 8 recall: 0.9092\nThread 8 latency: 24409\nThread 8 network latency: 13352.8\nThread 8 duration_meta_search: 6.198\nThread 8 compute time: 10788.2\nThread 9 recall: 0.901\nThread 9 latency: 24569\nThread 9 network latency: 13255.8\nThread 9 duration_meta_search: 7.884\nThread 9 compute time: 10782.1\n",
      "machine_record_prefix_interleavings": 0,
      "meta_us": 6.4942,
      "network_us": 6771.865,
      "path": "/home/kvgroup/chaomei/graphbeyond-c1/evidence/vldb-multicn-formal-20260719f/raw/dhnsw/DEEP1M_d-HNSW_2cn_r0/c1.log",
      "processed_queries": 5000,
      "qps": 406.4966784011307,
      "recall": 0.9090600072999999,
      "sha256": "87f703423d5c2e3972f9e2d16763ef360ecaff9bcd8e19987811b8143a5b4ce7",
      "wall_seconds": 12.300223509
    }
  ],
  "repeat": 0,
  "system": "d-HNSW",
  "throughput_aggregation": "sum_of_concurrent_disjoint_client_shards"
}
